Metadata-Version: 1.0
Name: Sree-probability
Version: 1.2
Summary: Gaussian distributions
Home-page: UNKNOWN
Author: Sreedhar Gunda
Author-email: blueskybuildtech@gmail.com
License: UNKNOWN
Platform: UNKNOWN
